VisionDiff/__init__.py
VisionDiff/block.py
VisionDiff/rotary.py
VisionDiff-0.1.0.dist-info/LICENSE
VisionDiff-0.1.0.dist-info/METADATA
VisionDiff-0.1.0.dist-info/WHEEL
VisionDiff-0.1.0.dist-info/top_level.txt
VisionDiff-0.1.0.dist-info/RECORD
