Metadata-Version: 2.1
Name: VisionDiff
Version: 0.1.0
Summary: Using the [Differential Transformer](https://arxiv.org/abs/2410.05258) in a vision-friendly way, similar to [VisionMamba](https://github.com/kyegomez/VisionMamba).
Home-page: https://github.com/Aveygo/VisionDiff
Author: aveygo
Author-email: aveygo.au@gmail.com
License: GPLv3
Classifier: Development Status :: 3 - Alpha
Classifier: License :: OSI Approved :: GNU General Public License v3 (GPLv3)
Classifier: Natural Language :: English
Classifier: Operating System :: OS Independent
Classifier: Programming Language :: Python :: 3.6
Classifier: Topic :: Other/Nonlisted Topic
License-File: LICENSE
Requires-Dist: torch
Requires-Dist: numpy
Requires-Dist: einops
